transparent_image_generator/__init__.py
transparent_image_generator-0.0.1.dist-info/LICENSE
transparent_image_generator-0.0.1.dist-info/METADATA
transparent_image_generator-0.0.1.dist-info/WHEEL
transparent_image_generator-0.0.1.dist-info/top_level.txt
transparent_image_generator-0.0.1.dist-info/RECORD
